open3d/__init__.py
open3d/_build_config.py
open3d/app.py
open3d/web_visualizer.py
open3d/cpu/pybind.cp310-win_amd64.pyd
open3d/examples/__init__.py
open3d/examples/open3d_example.py
open3d/examples/benchmark/__init__.py
open3d/examples/benchmark/benchmark_fgr.py
open3d/examples/benchmark/benchmark_nns.py
open3d/examples/benchmark/benchmark_pre.py
open3d/examples/benchmark/benchmark_ransac.py
open3d/examples/benchmark/benchmark_tsdf.py
open3d/examples/benchmark/benchmark_utils.py
open3d/examples/camera/camera_trajectory.py
open3d/examples/geometry/__init__.py
open3d/examples/geometry/image_processing.py
open3d/examples/geometry/kd_tree_feature_matching.py
open3d/examples/geometry/kd_tree_search.py
open3d/examples/geometry/octree_find_leaf.py
open3d/examples/geometry/octree_from_voxel_grid.py
open3d/examples/geometry/octree_point_cloud.py
open3d/examples/geometry/octree_traversal.py
open3d/examples/geometry/point_cloud_bounding_box.py
open3d/examples/geometry/point_cloud_convex_hull.py
open3d/examples/geometry/point_cloud_crop.py
open3d/examples/geometry/point_cloud_dbscan_clustering.py
open3d/examples/geometry/point_cloud_distance.py
open3d/examples/geometry/point_cloud_farthest_point_sampling.py
open3d/examples/geometry/point_cloud_hidden_point_removal.py
open3d/examples/geometry/point_cloud_iss_keypoint_detector.py
open3d/examples/geometry/point_cloud_normal_estimation.py
open3d/examples/geometry/point_cloud_outlier_removal_radius.py
open3d/examples/geometry/point_cloud_outlier_removal_statistical.py
open3d/examples/geometry/point_cloud_paint.py
open3d/examples/geometry/point_cloud_plane_segmentation.py
open3d/examples/geometry/point_cloud_to_depth.py
open3d/examples/geometry/point_cloud_to_rgbd.py
open3d/examples/geometry/point_cloud_transformation.py
open3d/examples/geometry/point_cloud_voxel_downsampling.py
open3d/examples/geometry/point_cloud_with_numpy.py
open3d/examples/geometry/ray_casting_closest_geometry.py
open3d/examples/geometry/ray_casting_sdf.py
open3d-0.18.0.dist-info/LICENSE.txt
open3d-0.18.0.dist-info/METADATA
open3d-0.18.0.dist-info/WHEEL
open3d-0.18.0.dist-info/entry_points.txt
open3d-0.18.0.dist-info/top_level.txt
open3d-0.18.0.dist-info/RECORD
