Metadata-Version: 2.1
Name: open3d
Version: 0.18.0
Summary: Open3D: A Modern Library for 3D Data Processing.
Home-page: https://www.open3d.org
Author: Open3D Team
Author-email: info@open3d.org
License: MIT
Project-URL: Documentation, https://www.open3d.org/docs
Project-URL: Source code, https://github.com/isl-org/Open3D
Project-URL: Issues, https://github.com/isl-org/Open3D/issues
Keywords: 3D reconstruction point cloud mesh RGB-D visualization
Classifier: Development Status :: 3 - Alpha
Classifier: Environment :: MacOS X
Classifier: Environment :: Win32 (MS Windows)
Classifier: Environment :: X11 Applications
Classifier: Environment :: GPU :: NVIDIA CUDA
Classifier: Intended Audience :: Developers
Classifier: Intended Audience :: Education
Classifier: Intended Audience :: Other Audience
Classifier: Intended Audience :: Science/Research
Classifier: License :: OSI Approved :: MIT License
Classifier: Natural Language :: English
Classifier: Operating System :: POSIX :: Linux
Classifier: Operating System :: MacOS :: MacOS X
Classifier: Operating System :: Microsoft :: Windows
Classifier: Programming Language :: C
Classifier: Programming Language :: C++
Classifier: Programming Language :: Python :: 3
Classifier: Programming Language :: Python :: 3.8
Classifier: Programming Language :: Python :: 3.9
Classifier: Programming Language :: Python :: 3.10
Classifier: Programming Language :: Python :: 3.11
Classifier: Topic :: Education
Classifier: Topic :: Multimedia :: Graphics :: 3D Modeling
Classifier: Topic :: Multimedia :: Graphics :: 3D Rendering
Classifier: Topic :: Multimedia :: Graphics :: Capture
Classifier: Topic :: Multimedia :: Graphics :: Graphics Conversion
Classifier: Topic :: Multimedia :: Graphics :: Viewers
Classifier: Topic :: Scientific/Engineering
Classifier: Topic :: Scientific/Engineering :: Mathematics
Classifier: Topic :: Scientific/Engineering :: Visualization
Classifier: Topic :: Software Development :: Libraries :: Python Modules
Classifier: Topic :: Utilities
Provides: open3d
Provides: open3d_cpu
Obsoletes: open3d_python
Requires-Python: >=3.8
License-File: LICENSE.txt
Requires-Dist: numpy (>=1.18.0)
Requires-Dist: dash (>=2.6.0)
Requires-Dist: werkzeug (>=2.2.3)
Requires-Dist: nbformat (>=5.7.0)
Requires-Dist: configargparse
Requires-Dist: ipywidgets (>=8.0.4)
Requires-Dist: pywinpty (==2.0.2) ; sys_platform == "win32" and python_version == "3.6"
